<?xml version="1.0" encoding="UTF-8" standalone="yes"?>
<w:hdr xmlns:wpc="http://schemas.microsoft.com/office/word/2010/wordprocessingCanvas" xmlns:cx="http://schemas.microsoft.com/office/drawing/2014/chartex" xmlns:cx1="http://schemas.microsoft.com/office/drawing/2015/9/8/chartex" xmlns:cx2="http://schemas.microsoft.com/office/drawing/2015/10/21/chartex" xmlns:cx3="http://schemas.microsoft.com/office/drawing/2016/5/9/chartex" xmlns:cx4="http://schemas.microsoft.com/office/drawing/2016/5/10/chartex" xmlns:cx5="http://schemas.microsoft.com/office/drawing/2016/5/11/chartex" xmlns:cx6="http://schemas.microsoft.com/office/drawing/2016/5/12/chartex" xmlns:cx7="http://schemas.microsoft.com/office/drawing/2016/5/13/chartex" xmlns:cx8="http://schemas.microsoft.com/office/drawing/2016/5/14/chartex" xmlns:mc="http://schemas.openxmlformats.org/markup-compatibility/2006" xmlns:aink="http://schemas.microsoft.com/office/drawing/2016/ink" xmlns:am3d="http://schemas.microsoft.com/office/drawing/2017/model3d" xmlns:o="urn:schemas-microsoft-com:office:office" xmlns:r="http://schemas.openxmlformats.org/officeDocument/2006/relationships" xmlns:m="http://schemas.openxmlformats.org/officeDocument/2006/math" xmlns:v="urn:schemas-microsoft-com:vml" xmlns:wp14="http://schemas.microsoft.com/office/word/2010/wordprocessingDrawing" xmlns:wp="http://schemas.openxmlformats.org/drawingml/2006/wordprocessingDrawing" xmlns:w10="urn:schemas-microsoft-com:office:word" xmlns:w="http://schemas.openxmlformats.org/wordprocessingml/2006/main" xmlns:w14="http://schemas.microsoft.com/office/word/2010/wordml" xmlns:w15="http://schemas.microsoft.com/office/word/2012/wordml" xmlns:w16cex="http://schemas.microsoft.com/office/word/2018/wordml/cex" xmlns:w16cid="http://schemas.microsoft.com/office/word/2016/wordml/cid" xmlns:w16="http://schemas.microsoft.com/office/word/2018/wordml" xmlns:w16sdtdh="http://schemas.microsoft.com/office/word/2020/wordml/sdtdatahash" xmlns:w16se="http://schemas.microsoft.com/office/word/2015/wordml/symex" xmlns:wpg="http://schemas.microsoft.com/office/word/2010/wordprocessingGroup" xmlns:wpi="http://schemas.microsoft.com/office/word/2010/wordprocessingInk" xmlns:wne="http://schemas.microsoft.com/office/word/2006/wordml" xmlns:wps="http://schemas.microsoft.com/office/word/2010/wordprocessingShape" mc:Ignorable="w14 w15 w16se w16cid w16 w16cex w16sdtdh wp14"><w:p w14:paraId="6365EF46" w14:textId="31F94283" w:rsidR="006D43EF" w:rsidRDefault="006D43EF" w:rsidP="009B43D3"><w:pPr><w:pStyle w:val="NormalWeb"/><w:spacing w:before="99" w:beforeAutospacing="0" w:after="0" w:afterAutospacing="0"/><w:ind w:left="142" w:right="425"/><w:jc w:val="center"/></w:pPr><w:bookmarkStart w:id="0" w:name="_Hlk155101707"/><w:bookmarkStart w:id="1" w:name="_Hlk188525821"/><w:bookmarkStart w:id="2" w:name="_Hlk188525822"/><w:r><w:rPr><w:noProof/></w:rPr><mc:AlternateContent><mc:Choice Requires="wps"><w:drawing><wp:anchor distT="0" distB="0" distL="114300" distR="114300" simplePos="0" relativeHeight="251659264" behindDoc="0" locked="0" layoutInCell="1" allowOverlap="1" wp14:anchorId="656EF4DF" wp14:editId="6CB4E9E6"><wp:simplePos x="0" y="0"/><wp:positionH relativeFrom="column"><wp:posOffset>-730885</wp:posOffset></wp:positionH><wp:positionV relativeFrom="paragraph"><wp:posOffset>-274955</wp:posOffset></wp:positionV><wp:extent cx="1026160" cy="834390"/><wp:effectExtent l="0" t="0" r="0" b="0"/><wp:wrapNone/><wp:docPr id="1776273873" name="Rectángulo 1"/><wp:cNvGraphicFramePr><a:graphicFrameLocks xmlns:a="http://schemas.openxmlformats.org/drawingml/2006/main"/></wp:cNvGraphicFramePr><a:graphic xmlns:a="http://schemas.openxmlformats.org/drawingml/2006/main"><a:graphicData uri="http://schemas.microsoft.com/office/word/2010/wordprocessingShape"><wps:wsp><wps:cNvSpPr><a:spLocks noChangeArrowheads="1"/></wps:cNvSpPr><wps:spPr bwMode="auto"><a:xfrm><a:off x="0" y="0"/><a:ext cx="1026160" cy="834390"/></a:xfrm><a:prstGeom prst="rect"><a:avLst/></a:prstGeom><a:solidFill><a:srgbClr val="FFFFFF"/></a:solidFill><a:ln><a:noFill/></a:ln></wps:spPr><wps:txbx><w:txbxContent><w:p w14:paraId="5A879972" w14:textId="77777777" w:rsidR="006D43EF" w:rsidRDefault="006D43EF" w:rsidP="006D43EF"><w:r w:rsidRPr="006D2503"><w:rPr><w:noProof/></w:rPr><w:drawing><wp:inline distT="0" distB="0" distL="0" distR="0" wp14:anchorId="3DE522E6" wp14:editId="1A789E95"><wp:extent cx="779228" cy="790590"/><wp:effectExtent l="0" t="0" r="0" b="0"/><wp:docPr id="546042798" name="Imagen 546042798"/><wp:cNvGraphicFramePr><a:graphicFrameLocks xmlns:a="http://schemas.openxmlformats.org/drawingml/2006/main" noChangeAspect="1"/></wp:cNvGraphicFramePr><a:graphic xmlns:a="http://schemas.openxmlformats.org/drawingml/2006/main"><a:graphicData uri="http://schemas.openxmlformats.org/drawingml/2006/picture"><pic:pic xmlns:pic="http://schemas.openxmlformats.org/drawingml/2006/picture"><pic:nvPicPr><pic:cNvPr id="1897055641" name=""/><pic:cNvPicPr/></pic:nvPicPr><pic:blipFill rotWithShape="1"><a:blip r:embed="rId1"/><a:srcRect l="7610" t="4980" r="8749" b="11800"/><a:stretch/></pic:blipFill><pic:spPr bwMode="auto"><a:xfrm><a:off x="0" y="0"/><a:ext cx="812871" cy="824723"/></a:xfrm><a:prstGeom prst="rect"><a:avLst/></a:prstGeom><a:ln><a:noFill/></a:ln><a:extLst><a:ext uri="{53640926-AAD7-44D8-BBD7-CCE9431645EC}"><a14:shadowObscured xmlns:a14="http://schemas.microsoft.com/office/drawing/2010/main"/></a:ext></a:extLst></pic:spPr></pic:pic></a:graphicData></a:graphic></wp:inline></w:drawing></w:r></w:p></w:txbxContent></wps:txbx><wps:bodyPr rot="0" vert="horz" wrap="square" lIns="91440" tIns="45720" rIns="91440" bIns="45720" anchor="t" anchorCtr="0" upright="1"><a:noAutofit/></wps:bodyPr></wps:wsp></a:graphicData></a:graphic><wp14:sizeRelH relativeFrom="page"><wp14:pctWidth>0</wp14:pctWidth></wp14:sizeRelH><wp14:sizeRelV relativeFrom="page"><wp14:pctHeight>0</wp14:pctHeight></wp14:sizeRelV></wp:anchor></w:drawing></mc:Choice><mc:Fallback><w:pict><v:rect w14:anchorId="656EF4DF" id="Rectángulo 1" o:spid="_x0000_s1026" style="position:absolute;left:0;text-align:left;margin-left:-57.55pt;margin-top:-21.65pt;width:80.8pt;height:65.7pt;z-index:251659264;visibility:visible;mso-wrap-style:square;mso-width-percent:0;mso-height-percent:0;mso-wrap-distance-left:9pt;mso-wrap-distance-top:0;mso-wrap-distance-right:9pt;mso-wrap-distance-bottom:0;mso-position-horizontal:absolute;mso-position-horizontal-relative:text;mso-position-vertical:absolute;mso-position-vertical-relative:text;mso-width-percent:0;mso-height-percent:0;mso-width-relative:page;mso-height-relative:page;v-text-anchor:top" o:gfxdata="UEsDBBQABgAIAAAAIQC2gziS/gAAAOEBAAATAAAAW0NvbnRlbnRfVHlwZXNdLnhtbJSRQU7DMBBF&#xA;90jcwfIWJU67QAgl6YK0S0CoHGBkTxKLZGx5TGhvj5O2G0SRWNoz/78nu9wcxkFMGNg6quQqL6RA&#xA;0s5Y6ir5vt9lD1JwBDIwOMJKHpHlpr69KfdHjyxSmriSfYz+USnWPY7AufNIadK6MEJMx9ApD/oD&#xA;OlTrorhX2lFEilmcO2RdNtjC5xDF9pCuTyYBB5bi6bQ4syoJ3g9WQ0ymaiLzg5KdCXlKLjvcW893&#xA;SUOqXwnz5DrgnHtJTxOsQfEKIT7DmDSUCaxw7Rqn8787ZsmRM9e2VmPeBN4uqYvTtW7jvijg9N/y&#xA;JsXecLq0q+WD6m8AAAD//wMAUEsDBBQABgAIAAAAIQA4/SH/1gAAAJQBAAALAAAAX3JlbHMvLnJl&#xA;bHOkkMFqwzAMhu+DvYPRfXGawxijTi+j0GvpHsDYimMaW0Yy2fr2M4PBMnrbUb/Q94l/f/hMi1qR&#xA;JVI2sOt6UJgd+ZiDgffL8ekFlFSbvV0oo4EbChzGx4f9GRdb25HMsYhqlCwG5lrLq9biZkxWOiqY&#xA;22YiTra2kYMu1l1tQD30/bPm3wwYN0x18gb45AdQl1tp5j/sFB2T0FQ7R0nTNEV3j6o9feQzro1i&#xA;OWA14Fm+Q8a1a8+Bvu/d/dMb2JY5uiPbhG/ktn4cqGU/er3pcvwCAAD//wMAUEsDBBQABgAIAAAA&#xA;IQAMN7LaEQIAAPEDAAAOAAAAZHJzL2Uyb0RvYy54bWysU1GO0zAQ/UfiDpb/aZq2tN2o6WrVVRHS&#xA;AisWDuA4TmKReMzYbVJuw1m4GGOnWwr8IfxheTwzz/PejDe3Q9eyo0KnweQ8nUw5U0ZCqU2d88+f&#xA;9q/WnDkvTClaMCrnJ+X47fbli01vMzWDBtpSISMQ47Le5rzx3mZJ4mSjOuEmYJUhZwXYCU8m1kmJ&#xA;oif0rk1m0+ky6QFLiyCVc3R7Pzr5NuJXlZL+Q1U55Vmbc6rNxx3jXoQ92W5EVqOwjZbnMsQ/VNEJ&#xA;bejRC9S98IIdUP8F1WmJ4KDyEwldAlWlpYociE06/YPNUyOsilxIHGcvMrn/ByvfHx+R6ZJ6t1ot&#xA;Z6v5ejXnzIiOevWR1Pvx3dSHFlgalOqtyyjhyT5i4OrsA8gvjhnYNcLU6g4R+kaJkuqL8clvCcFw&#xA;lMqK/h2UhC8OHqJoQ4VdACQ52BB7c7r0Rg2eSbpMp7NluqQWSvKt54v5TWxeIrLnbIvOv1HQsXDI&#xA;OVL1EV0cH5yn6in0OSRWD60u97pto4F1sWuRHQXNyT6uQJhS3HVYa0KwgZA2usNNpBmYjQr5oRjO&#xA;YhVQnogwwjh39E/o0AB+46ynmcu5+3oQqDhr3xoS7SZdLMKQRmPxejUjA689xbVHGElQOfecjced&#xA;Hwf7YFHXDb2URv4G7kjoSkcNQhPGqs5101xFnuc/EAb32o5Rv37q9icAAAD//wMAUEsDBBQABgAI&#xA;AAAAIQALfTwl3wAAAAoBAAAPAAAAZHJzL2Rvd25yZXYueG1sTI/LTsMwEEX3SPyDNUjsWtvkoZDG&#xA;qRBSV8CCFontNHaTqPE4xE4b/h6zgt2M5ujOudV2sQO7mMn3jhTItQBmqHG6p1bBx2G3KoD5gKRx&#xA;cGQUfBsP2/r2psJSuyu9m8s+tCyGkC9RQRfCWHLum85Y9Gs3Goq3k5sshrhOLdcTXmO4HfiDEDm3&#xA;2FP80OFonjvTnPezVYB5qr/eTsnr4WXO8bFdxC77FErd3y1PG2DBLOEPhl/9qA51dDq6mbRng4KV&#xA;lJmMbJzSJAEWkTTPgB0VFIUEXlf8f4X6BwAA//8DAFBLAQItABQABgAIAAAAIQC2gziS/gAAAOEB&#xA;AAATAAAAAAAAAAAAAAAAAAAAAABbQ29udGVudF9UeXBlc10ueG1sUEsBAi0AFAAGAAgAAAAhADj9&#xA;If/WAAAAlAEAAAsAAAAAAAAAAAAAAAAALwEAAF9yZWxzLy5yZWxzUEsBAi0AFAAGAAgAAAAhAAw3&#xA;stoRAgAA8QMAAA4AAAAAAAAAAAAAAAAALgIAAGRycy9lMm9Eb2MueG1sUEsBAi0AFAAGAAgAAAAh&#xA;AAt9PCXfAAAACgEAAA8AAAAAAAAAAAAAAAAAawQAAGRycy9kb3ducmV2LnhtbFBLBQYAAAAABAAE&#xA;APMAAAB3BQAAAAA=&#xA;" stroked="f"><v:textbox><w:txbxContent><w:p w14:paraId="5A879972" w14:textId="77777777" w:rsidR="006D43EF" w:rsidRDefault="006D43EF" w:rsidP="006D43EF"><w:r w:rsidRPr="006D2503"><w:rPr><w:noProof/></w:rPr><w:drawing><wp:inline distT="0" distB="0" distL="0" distR="0" wp14:anchorId="3DE522E6" wp14:editId="1A789E95"><wp:extent cx="779228" cy="790590"/><wp:effectExtent l="0" t="0" r="0" b="0"/><wp:docPr id="546042798" name="Imagen 546042798"/><wp:cNvGraphicFramePr><a:graphicFrameLocks xmlns:a="http://schemas.openxmlformats.org/drawingml/2006/main" noChangeAspect="1"/></wp:cNvGraphicFramePr><a:graphic xmlns:a="http://schemas.openxmlformats.org/drawingml/2006/main"><a:graphicData uri="http://schemas.openxmlformats.org/drawingml/2006/picture"><pic:pic xmlns:pic="http://schemas.openxmlformats.org/drawingml/2006/picture"><pic:nvPicPr><pic:cNvPr id="1897055641" name=""/><pic:cNvPicPr/></pic:nvPicPr><pic:blipFill rotWithShape="1"><a:blip r:embed="rId1"/><a:srcRect l="7610" t="4980" r="8749" b="11800"/><a:stretch/></pic:blipFill><pic:spPr bwMode="auto"><a:xfrm><a:off x="0" y="0"/><a:ext cx="812871" cy="824723"/></a:xfrm><a:prstGeom prst="rect"><a:avLst/></a:prstGeom><a:ln><a:noFill/></a:ln><a:extLst><a:ext uri="{53640926-AAD7-44D8-BBD7-CCE9431645EC}"><a14:shadowObscured xmlns:a14="http://schemas.microsoft.com/office/drawing/2010/main"/></a:ext></a:extLst></pic:spPr></pic:pic></a:graphicData></a:graphic></wp:inline></w:drawing></w:r></w:p></w:txbxContent></v:textbox></v:rect></w:pict></mc:Fallback></mc:AlternateContent></w:r><w:r><w:rPr><w:rFonts w:ascii="Arial Narrow" w:hAnsi="Arial Narrow"/><w:bCs/><w:color w:val="231F20"/></w:rPr><w:t>“</w:t></w:r><w:bookmarkEnd w:id="0"/><w:r w:rsidR="009B43D3" w:rsidRPr="009B43D3"><w:rPr><w:rFonts w:ascii="Arial Narrow" w:hAnsi="Arial Narrow"/><w:bCs/><w:color w:val="231F20"/></w:rPr><w:t>Año de la recuperación y consolidación de la economía peruana”</w:t></w:r><w:bookmarkEnd w:id="1"/><w:bookmarkEnd w:id="2"/></w:p></w:hdr>